{
  "main": {
    "id": "e9ca431d8a569203",
    "type": "split",
    "children": [
      {
        "id": "2ee4eb6331771ee0",
        "type": "tabs",
        "children": [
          {
            "id": "f0569fba17afd26d",
            "type": "leaf",
            "state": {
              "type": "graph",
              "state": {},
              "icon": "lucide-git-fork",
              "title": "그래프 뷰"
            }
          }
        ]
      }
    ],
    "direction": "vertical"
  },
  "left": {
    "id": "4c5b4669c67e3cc2",
    "type": "split",
    "children": [
      {
        "id": "4f3e867f71923f43",
        "type": "tabs",
        "children": [
          {
            "id": "9d65714895d17178",
            "type": "leaf",
            "state": {
              "type": "file-explorer",
              "state": {
                "sortOrder": "alphabetical",
                "autoReveal": false
              },
              "icon": "lucide-folder-closed",
              "title": "파일 탐색기"
            }
          },
          {
            "id": "17e43d8a9babe0c7",
            "type": "leaf",
            "state": {
              "type": "search",
              "state": {
                "query": "",
                "matchingCase": false,
                "explainSearch": false,
                "collapseAll": false,
                "extraContext": false,
                "sortOrder": "alphabetical"
              },
              "icon": "lucide-search",
              "title": "검색"
            }
          },
          {
            "id": "372a9f04708072cf",
            "type": "leaf",
            "state": {
              "type": "bookmarks",
              "state": {},
              "icon": "lucide-bookmark",
              "title": "북마크"
            }
          }
        ]
      }
    ],
    "direction": "horizontal",
    "width": 300
  },
  "right": {
    "id": "c58cbd69ff36ab2d",
    "type": "split",
    "children": [
      {
        "id": "df420461f572a556",
        "type": "tabs",
        "children": [
          {
            "id": "2e7f71c22f17d514",
            "type": "leaf",
            "state": {
              "type": "backlink",
              "state": {
                "collapseAll": false,
                "extraContext": false,
                "sortOrder": "alphabetical",
                "showSearch": false,
                "searchQuery": "",
                "backlinkCollapsed": false,
                "unlinkedCollapsed": true
              },
              "icon": "links-coming-in",
              "title": "백링크"
            }
          },
          {
            "id": "8e3db6872eb5789f",
            "type": "leaf",
            "state": {
              "type": "tag",
              "state": {
                "sortOrder": "frequency",
                "useHierarchy": true,
                "showSearch": false,
                "searchQuery": ""
              },
              "icon": "lucide-tags",
              "title": "태그"
            }
          },
          {
            "id": "1ee8e8892e5c6ba2",
            "type": "leaf",
            "state": {
              "type": "all-properties",
              "state": {
                "sortOrder": "frequency",
                "showSearch": false,
                "searchQuery": ""
              },
              "icon": "lucide-archive",
              "title": "모든 속성"
            }
          }
        ]
      }
    ],
    "direction": "horizontal",
    "width": 300,
    "collapsed": true
  },
  "left-ribbon": {
    "hiddenItems": {
      "switcher:빠른 전환기 열기": false,
      "graph:그래프 뷰 열기": false,
      "canvas:새 캔버스 만들기": false,
      "command-palette:명령어 팔레트 열기": false,
      "bases:새 베이스 생성하기": false
    }
  },
  "active": "f0569fba17afd26d",
  "lastOpenFiles": [
    "법령/법령-환경측정기기고시.md",
    "정도검사/정도검사-항목별기준.md",
    "search-index.json",
    "embeddings.json",
    "공통/용어-관계도.md",
    "정도관리규정/정도관리규정-점검표.md",
    "정도관리규정/정도관리규정-절차-서식.md",
    "정도관리규정/정도관리규정-요구사항-평가분야.md",
    "정도관리규정",
    "대기공정시험기준/ES01900-굴뚝연속자동측정-CEMS.md",
    "대기공정시험기준/ES01600-환경대기-측정방법.md",
    "대기공정시험기준/ES01500-유기화합물-VOC.md",
    "대기공정시험기준/ES01400-금속화합물-배출가스.md",
    "대기공정시험기준/ES01303-배출가스-가스상항목.md",
    "대기공정시험기준/ES01301-먼지-배출가스.md",
    "대기공정시험기준/ES01100-시료채취방법.md",
    "대기공정시험기준/ES01000-총칙-정도보증.md",
    "대기공정시험기준",
    "먹는물공정시험기준/ES05700-미생물-세균-대장균군.md",
    "먹는물공정시험기준/ES05500-유기화합물개요.md",
    "먹는물공정시험기준/ES05400-금속류.md",
    "먹는물공정시험기준/ES05310-CL-잔류염소.md",
    "먹는물공정시험기준/ES05308-TU-탁도.md",
    "먹는물공정시험기준/ES05306-pH-수소이온농도.md",
    "먹는물공정시험기준/ES05300-일반화학항목.md",
    "먹는물공정시험기준/ES05000-총칙-정도보증.md",
    "먹는물공정시험기준",
    "공통/KTL-서비스안내.md",
    "법령/법령-물환경보전법-TMS조항.md",
    "법령/법령-고시-별표3-수질정도검사점검표.md",
    "법령/법령-고시-별표7의1-정도검사주기-2013년이전.md",
    "수질공정시험기준",
    "성능시험/성능시험-항목별기준.md.tmp.3092.92b00e3f7b95",
    "공통",
    "법령",
    "표준용액"
  ]
}